clickyaml/__init__.py
clickyaml/clickyaml.py
clickyaml/commander.py
clickyaml-2.1.0.dist-info/AUTHORS.rst
clickyaml-2.1.0.dist-info/LICENSE
clickyaml-2.1.0.dist-info/METADATA
clickyaml-2.1.0.dist-info/WHEEL
clickyaml-2.1.0.dist-info/top_level.txt
clickyaml-2.1.0.dist-info/RECORD
