Metadata-Version: 2.1
Name: clickyaml
Version: 2.1.0
Summary: ClickYaml reads a `.yaml` file and creates click Commands out of it.
Home-page: https://github.com/vandyG/clickyaml
Author: Vandit Goel
Author-email: vandy.goel23@gmail.com
License: MIT license
Keywords: clickyaml
Classifier: Development Status :: 2 - Pre-Alpha
Classifier: Intended Audience :: Developers
Classifier: License :: OSI Approved :: MIT License
Classifier: Natural Language :: English
Classifier: Programming Language :: Python :: 3
Classifier: Programming Language :: Python :: 3.11
Classifier: Programming Language :: Python :: 3.10
Classifier: Programming Language :: Python :: 3.9
Classifier: Programming Language :: Python :: 3.8
Classifier: Programming Language :: Python :: 3.7
Requires-Python: >=3.7
License-File: LICENSE
License-File: AUTHORS.rst
Requires-Dist: Click (>=7.0)
Requires-Dist: python-dotenv
Requires-Dist: pyyaml
